.env.example
README.md
pynions.example.json
pytest.ini
requirements.txt
docs/changelog.md
docs/configuration.md
docs/data-organization.md
docs/debugging.md
docs/index.md
docs/installation.md
docs/nav.json
docs/plugins.md
docs/project-structure.md
docs/quickstart.md
docs/testing.md
docs/workers.md
docs/workflows.md
docs/examples/advanced.py
docs/examples/bofu_ideas.md
docs/examples/bofu_ideas.py
docs/examples/examples.md
docs/plugins/frase.md
docs/plugins/jina.md
docs/plugins/litellm_plugin.md
docs/plugins/serper.md
docs/templates/templates.md
docs/use-cases/use-cases.md
docs/workflows/content_analysis.md
pynions/__init__.py
pynions/__pycache__/__init__.cpython-312.pyc
pynions/core/__init__.py
pynions/core/config.py
pynions/core/datastore.py
pynions/core/plugin.py
pynions/core/utils.py
pynions/core/worker.py
pynions/core/workflow.py
pynions/core/__pycache__/__init__.cpython-312.pyc
pynions/core/__pycache__/config.cpython-312.pyc
pynions/core/__pycache__/datastore.cpython-312.pyc
pynions/core/__pycache__/plugin.cpython-312.pyc
pynions/core/__pycache__/worker.cpython-312.pyc
pynions/core/__pycache__/workflow.cpython-312.pyc
pynions/plugins/__init__.py
pynions/plugins/base.py
pynions/plugins/frase.py
pynions/plugins/jina.py
pynions/plugins/litellm_plugin.py
pynions/plugins/serper.py
pynions/plugins/stats.py
pynions/plugins/__pycache__/__init__.cpython-312.pyc
pynions/plugins/__pycache__/base.cpython-312.pyc
pynions/plugins/__pycache__/jina.cpython-312.pyc
pynions/plugins/__pycache__/litellm_plugin.cpython-312.pyc
pynions/plugins/__pycache__/serper.cpython-312.pyc
pynions/plugins/__pycache__/stats.cpython-312.pyc
pynions/tests/__init__.py
pynions/tests/conftest.py
pynions/tests/test_core.py
pynions/tests/test_plugins/test_serper_plugin.py
pynions/workers/alternatives_analysis_worker.py
pynions/workers/alternatives_search_worker.py
pynions/workers/company_data_worker.py
pynions/workers/pricing_research_worker.py
pynions-0.2.32.dist-info/LICENSE
pynions-0.2.32.dist-info/METADATA
pynions-0.2.32.dist-info/WHEEL
pynions-0.2.32.dist-info/top_level.txt
pynions-0.2.32.dist-info/RECORD
