Metadata-Version: 2.1
Name: pynions
Version: 0.2.32
Summary: Simple marketing automation framework
Home-page: https://github.com/craftled/pynions
Author: Tomas Laurinavicius
Author-email: tom@pynions.com
Classifier: Development Status :: 4 - Beta
Classifier: Intended Audience :: End Users/Desktop
Classifier: License :: OSI Approved :: MIT License
Classifier: Operating System :: OS Independent
Classifier: Programming Language :: Python :: 3
Classifier: Programming Language :: Python :: 3.8
Classifier: Topic :: Office/Business
Requires-Python: >=3.8
License-File: LICENSE
Requires-Dist: aiohttp <3.11.0,>=3.10.11
Requires-Dist: python-dotenv <2.0.0,>=1.0.1
Requires-Dist: pydantic <3.0.0,>=2.9.2
Requires-Dist: litellm <2.0.0,>=1.51.3
Requires-Dist: playwright <2.0.0,>=1.48.0
Requires-Dist: httpx <0.28.0,>=0.27.2
Requires-Dist: pip >=24.3.1
Requires-Dist: setuptools >=75.3.0
Requires-Dist: pytest >=8.3.3
Requires-Dist: pytest-asyncio >=0.24.0
Requires-Dist: pytest-cov >=6.0.0
Requires-Dist: black >=24.10.0
Requires-Dist: isort >=5.13.2
